pyhtool/Operator.py
pyhtool/QRCode.py
pyhtool/Verification.py
pyhtool/__init__.py
pyhtool-0.1.1.dist-info/licenses/LICENSE
pyhtool-0.1.1.dist-info/METADATA
pyhtool-0.1.1.dist-info/WHEEL
pyhtool-0.1.1.dist-info/top_level.txt
pyhtool-0.1.1.dist-info/RECORD
