Metadata-Version: 2.4
Name: pyhtool
Version: 0.1.1
Summary: Pyhtool lets Python control the mouse and keyboard, and other GUI automation tasks. For Windows, macOS, and Linux
Home-page: https://github.com/nydia/pyhtool
Author: nydia
Author-email: nydia_lhq@hotmail.com
License: BSD
Keywords: gui automation test testing keyboard mouse cursor click press keystroke control
Classifier: Development Status :: 4 - Beta
Classifier: Environment :: Win32 (MS Windows)
Classifier: Environment :: X11 Applications
Classifier: Environment :: MacOS X
Classifier: Intended Audience :: Developers
Classifier: License :: OSI Approved :: BSD License
Classifier: Operating System :: OS Independent
Classifier: Programming Language :: Python
Classifier: Programming Language :: Python :: 2
Classifier: Programming Language :: Python :: 2.7
Classifier: Programming Language :: Python :: 3
Classifier: Programming Language :: Python :: 3.1
Classifier: Programming Language :: Python :: 3.2
Classifier: Programming Language :: Python :: 3.3
Classifier: Programming Language :: Python :: 3.4
Classifier: Programming Language :: Python :: 3.5
Classifier: Programming Language :: Python :: 3.6
Classifier: Programming Language :: Python :: 3.7
Classifier: Programming Language :: Python :: 3.8
Classifier: Programming Language :: Python :: 3.9
Classifier: Programming Language :: Python :: 3.10
Classifier: Programming Language :: Python :: 3.11
License-File: LICENSE
Requires-Dist: pyobjc-core; platform_system == "Darwin"
Requires-Dist: pyobjc; platform_system == "Darwin"
Requires-Dist: python3-Xlib; platform_system == "Linux" and python_version >= "3.0"
Requires-Dist: python-xlib; platform_system == "Linux" and python_version < "3.0"
Requires-Dist: pymsgbox
Requires-Dist: pytweening>=1.0.4
Requires-Dist: pyscreeze>=0.1.21
Requires-Dist: pygetwindow>=0.0.5
Requires-Dist: mouseinfo
Dynamic: author
Dynamic: author-email
Dynamic: classifier
Dynamic: description
Dynamic: description-content-type
Dynamic: home-page
Dynamic: keywords
Dynamic: license
Dynamic: license-file
Dynamic: requires-dist
Dynamic: summary
